{
    "imgHeight": 1024,
    "imgWidth": 2048,
    "objects": [
        {
            "label": "background",
            "polygon": [
                [
                    290,
                    952
                ],
                [
                    294,
                    954
                ],
                [
                    1043,
                    926
                ],
                [
                    1284,
                    922
                ],
                [
                    1478,
                    924
                ],
                [
                    1984,
                    967
                ],
                [
                    1984,
                    963
                ],
                [
                    1600,
                    698
                ],
                [
                    1592,
                    698
                ],
                [
                    1426,
                    586
                ],
                [
                    1321,
                    539
                ],
                [
                    1236,
                    506
                ],
                [
                    1210,
                    506
                ],
                [
                    1171,
                    508
                ],
                [
                    1151,
                    513
                ],
                [
                    1076,
                    517
                ],
                [
                    1047,
                    557
                ],
                [
                    797,
                    693
                ]
            ]
        },
        {
            "label": "background",
            "polygon": [
                [
                    88,
                    707
                ],
                [
                    69,
                    950
                ],
                [
                    460,
                    786
                ],
                [
                    463,
                    786
                ],
                [
                    775,
                    653
                ],
                [
                    980,
                    559
                ],
                [
                    1009,
                    550
                ],
                [
                    1054,
                    512
                ],
                [
                    1061,
                    503
                ],
                [
                    1033,
                    504
                ],
                [
                    996,
                    500
                ],
                [
                    995,
                    545
                ],
                [
                    993,
                    548
                ],
                [
                    986,
                    550
                ],
                [
                    982,
                    548
                ],
                [
                    978,
                    508
                ],
                [
                    936,
                    526
                ],
                [
                    935,
                    528
                ],
                [
                    903,
                    543
                ],
                [
                    859,
                    555
                ],
                [
                    804,
                    564
                ],
                [
                    446,
                    658
                ],
                [
                    360,
                    660
                ],
                [
                    285,
                    659
                ]
            ]
        },
        {
            "label": "background",
            "polygon": [
                [
                    894,
                    536
                ],
                [
                    896,
                    535
                ],
                [
                    902,
                    367
                ],
                [
                    900,
                    368
                ]
            ]
        },
        {
            "label": "background",
            "polygon": [
                [
                    937,
                    517
                ],
                [
                    938,
                    516
                ],
                [
                    940,
                    343
                ],
                [
                    939,
                    343
                ]
            ]
        },
        {
            "label": "background",
            "polygon": [
                [
                    987,
                    544
                ],
                [
                    989,
                    543
                ],
                [
                    987,
                    489
                ],
                [
                    985,
                    489
                ]
            ]
        },
        {
            "label": "background",
            "polygon": [
                [
                    982,
                    390
                ],
                [
                    984,
                    390
                ],
                [
                    981,
                    318
                ],
                [
                    979,
                    318
                ]
            ]
        },
        {
            "label": "background",
            "polygon": [
                [
                    1278,
                    445
                ],
                [
                    1265,
                    475
                ],
                [
                    1268,
                    488
                ],
                [
                    1276,
                    495
                ],
                [
                    1339,
                    498
                ],
                [
                    1361,
                    505
                ],
                [
                    1375,
                    515
                ],
                [
                    1395,
                    524
                ],
                [
                    1433,
                    530
                ],
                [
                    1470,
                    545
                ],
                [
                    1500,
                    546
                ],
                [
                    1529,
                    566
                ],
                [
                    1533,
                    575
                ],
                [
                    1540,
                    582
                ],
                [
                    1574,
                    602
                ],
                [
                    1587,
                    620
                ],
                [
                    1595,
                    624
                ],
                [
                    1646,
                    631
                ],
                [
                    1717,
                    630
                ],
                [
                    1757,
                    642
                ],
                [
                    1767,
                    652
                ],
                [
                    1774,
                    670
                ],
                [
                    1781,
                    720
                ],
                [
                    1798,
                    742
                ],
                [
                    1810,
                    740
                ],
                [
                    1826,
                    722
                ],
                [
                    1839,
                    719
                ],
                [
                    1858,
                    723
                ],
                [
                    1900,
                    739
                ],
                [
                    1963,
                    749
                ],
                [
                    2020,
                    772
                ],
                [
                    2032,
                    395
                ],
                [
                    1960,
                    425
                ],
                [
                    1900,
                    441
                ],
                [
                    1888,
                    440
                ],
                [
                    1854,
                    425
                ],
                [
                    1834,
                    421
                ],
                [
                    1684,
                    419
                ],
                [
                    1637,
                    423
                ],
                [
                    1576,
                    423
                ],
                [
                    1504,
                    436
                ],
                [
                    1391,
                    436
                ],
                [
                    1381,
                    459
                ],
                [
                    1348,
                    452
                ],
                [
                    1338,
                    448
                ],
                [
                    1312,
                    444
                ]
            ]
        },
        {
            "label": "background",
            "polygon": [
                [
                    1013,
                    6
                ],
                [
                    1022,
                    26
                ],
                [
                    1022,
                    31
                ],
                [
                    1025,
                    40
                ],
                [
                    1027,
                    64
                ],
                [
                    1180,
                    66
                ],
                [
                    1179,
                    66
                ],
                [
                    1181,
                    49
                ],
                [
                    1182,
                    45
                ],
                [
                    1188,
                    37
                ],
                [
                    1195,
                    35
                ],
                [
                    1204,
                    34
                ],
                [
                    1219,
                    43
                ],
                [
                    1221,
                    45
                ],
                [
                    1224,
                    59
                ],
                [
                    1227,
                    56
                ],
                [
                    1230,
                    3
                ],
                [
                    1012,
                    3
                ]
            ]
        },
        {
            "label": "background",
            "polygon": [
                [
                    1525,
                    70
                ],
                [
                    1474,
                    188
                ],
                [
                    1439,
                    258
                ],
                [
                    1443,
                    297
                ],
                [
                    1458,
                    317
                ],
                [
                    1489,
                    337
                ],
                [
                    1589,
                    341
                ],
                [
                    1628,
                    339
                ],
                [
                    1642,
                    335
                ],
                [
                    1657,
                    312
                ],
                [
                    1659,
                    282
                ],
                [
                    1653,
                    234
                ],
                [
                    1663,
                    177
                ],
                [
                    1672,
                    172
                ],
                [
                    1703,
                    171
                ],
                [
                    1725,
                    186
                ],
                [
                    1760,
                    194
                ],
                [
                    1782,
                    208
                ],
                [
                    1850,
                    238
                ],
                [
                    1863,
                    280
                ],
                [
                    1863,
                    344
                ],
                [
                    1877,
                    359
                ],
                [
                    1889,
                    364
                ],
                [
                    1910,
                    364
                ],
                [
                    1917,
                    358
                ],
                [
                    1924,
                    349
                ],
                [
                    1930,
                    327
                ],
                [
                    1965,
                    280
                ],
                [
                    1975,
                    273
                ],
                [
                    2004,
                    269
                ],
                [
                    2021,
                    253
                ],
                [
                    2029,
                    195
                ],
                [
                    2024,
                    24
                ],
                [
                    2006,
                    21
                ],
                [
                    1975,
                    29
                ],
                [
                    1767,
                    29
                ],
                [
                    1709,
                    53
                ],
                [
                    1693,
                    109
                ],
                [
                    1680,
                    128
                ],
                [
                    1656,
                    113
                ],
                [
                    1634,
                    71
                ],
                [
                    1608,
                    38
                ],
                [
                    1599,
                    32
                ],
                [
                    1588,
                    32
                ],
                [
                    1570,
                    56
                ]
            ]
        },
        {
            "label": "background",
            "polygon": [
                [
                    1674,
                    402
                ],
                [
                    1679,
                    402
                ],
                [
                    1679,
                    338
                ],
                [
                    1676,
                    339
                ]
            ]
        },
        {
            "label": "background",
            "polygon": [
                [
                    47,
                    25
                ],
                [
                    51,
                    43
                ],
                [
                    33,
                    594
                ],
                [
                    430,
                    597
                ],
                [
                    837,
                    505
                ],
                [
                    847,
                    391
                ],
                [
                    862,
                    279
                ],
                [
                    871,
                    266
                ],
                [
                    882,
                    257
                ],
                [
                    933,
                    269
                ],
                [
                    931,
                    269
                ],
                [
                    926,
                    248
                ],
                [
                    937,
                    197
                ],
                [
                    956,
                    182
                ],
                [
                    974,
                    173
                ],
                [
                    986,
                    177
                ],
                [
                    996,
                    188
                ],
                [
                    1044,
                    228
                ],
                [
                    1041,
                    278
                ],
                [
                    1044,
                    309
                ],
                [
                    1057,
                    313
                ],
                [
                    1158,
                    320
                ],
                [
                    1174,
                    314
                ],
                [
                    1213,
                    299
                ],
                [
                    1306,
                    272
                ],
                [
                    1321,
                    263
                ],
                [
                    1364,
                    262
                ],
                [
                    1390,
                    102
                ],
                [
                    1385,
                    22
                ],
                [
                    1262,
                    17
                ],
                [
                    1266,
                    24
                ],
                [
                    1246,
                    81
                ],
                [
                    1092,
                    93
                ],
                [
                    984,
                    72
                ],
                [
                    964,
                    10
                ]
            ]
        },
        {
            "label": "background",
            "polygon": [
                [
                    1756,
                    369
                ],
                [
                    1760,
                    369
                ],
                [
                    1759,
                    337
                ],
                [
                    1756,
                    338
                ]
            ]
        },
        {
            "label": "background",
            "polygon": [
                [
                    1757,
                    329
                ],
                [
                    1759,
                    328
                ],
                [
                    1761,
                    282
                ],
                [
                    1759,
                    283
                ]
            ]
        },
        {
            "label": "background",
            "polygon": [
                [
                    271,
                    1023
                ],
                [
                    387,
                    1009
                ],
                [
                    549,
                    993
                ],
                [
                    821,
                    966
                ],
                [
                    1082,
                    950
                ],
                [
                    1142,
                    947
                ],
                [
                    1112,
                    932
                ],
                [
                    1096,
                    896
                ],
                [
                    1108,
                    861
                ],
                [
                    1137,
                    844
                ],
                [
                    1175,
                    844
                ],
                [
                    1204,
                    867
                ],
                [
                    1209,
                    897
                ],
                [
                    1195,
                    931
                ],
                [
                    1161,
                    945
                ],
                [
                    1376,
                    957
                ],
                [
                    1654,
                    977
                ],
                [
                    1883,
                    1002
                ],
                [
                    2028,
                    1023
                ]
            ]
        },
        {
            "label": "background",
            "polygon": [
                [
                    0,
                    0
                ],
                [
                    2048,
                    0
                ],
                [
                    2048,
                    1024
                ],
                [
                    0,
                    1024
                ],
                [
                    0,
                    0
                ],
                [
                    5,
                    5
                ],
                [
                    5,
                    1019
                ],
                [
                    2043,
                    1019
                ],
                [
                    2043,
                    5
                ],
                [
                    5,
                    5
                ]
            ]
        }
    ]
}